ai_test_assistant_mcp/__init__.py
ai_test_assistant_mcp/server.py
ai_test_assistant_mcp-1.0.0.dist-info/METADATA
ai_test_assistant_mcp-1.0.0.dist-info/WHEEL
ai_test_assistant_mcp-1.0.0.dist-info/entry_points.txt
ai_test_assistant_mcp-1.0.0.dist-info/licenses/LICENSE
ai_test_assistant_mcp-1.0.0.dist-info/RECORD
