Metadata-Version: 2.4
Name: ai-test-assistant-mcp
Version: 1.0.0
Summary: AI 驱动的自动化测试助手 MCP Server - 生成AC、测试用例、UI/API自动化代码
Project-URL: Homepage, https://pypi.org/project/ai-test-assistant-mcp/
License: MIT
License-File: LICENSE
Keywords: ai,automation,copilot,mcp,pytest,selenium,testing
Classifier: Development Status :: 4 - Beta
Classifier: Intended Audience :: Developers
Classifier: License :: OSI Approved :: MIT License
Classifier: Programming Language :: Python :: 3
Classifier: Programming Language :: Python :: 3.10
Classifier: Programming Language :: Python :: 3.11
Classifier: Programming Language :: Python :: 3.12
Classifier: Topic :: Software Development :: Testing
Requires-Python: >=3.10
Requires-Dist: httpx>=0.24.0
Requires-Dist: mcp[cli]>=1.0.0
Requires-Dist: openai>=1.0.0
